{
  "notes": [72, 74, 76, 79, 81, 84, 86],
  "interval_upper": [1, 1, 1, 1, 1, 1, 1, 1, 2, 2],
  "interval_lower": [1, 1, 1, 1, 1, 1, 1, 1, 0],
  "rhythm": [
    [0.5, 0.5, 0.5, 0.25, 0.25, 0.5, 0.5, 1.0],
    [0.5, 0.5, 1.0, 0.5, 0.5, 1.0],
    [0.5, 0.5, 0.5, 0.25, 0.25, 0.25, 0.25, 0.5, 1.0],
    [0.5, 0.5, 1.0, 0.25, 0.25, 0.5, 1.0]
  ],
  "seq_chord": [
    [52, 55, 60],
    [52, 57, 60],
    [53, 57, 60],
    [55, 59, 62]
  ],
  "seq_perc": [
    [36, 0.5], [42, 0.5], [38, 0.5], [42, 0.5], [36, 0.5], [42, 0.5], [38, 0.5], [42, 0.5],
    [36, 0.5], [42, 0.5], [38, 0.5], [42, 0.5], [36, 0.5], [36, 0.5], [38, 0.5], [42, 0.5],
    [36, 0.5], [42, 0.5], [38, 0.5], [42, 0.5], [36, 0.5], [42, 0.5], [38, 0.5], [42, 0.5],
    [36, 0.5], [42, 0.5], [38, 0.5], [42, 0.5], [36, 0.5], [36, 0.5], [38, 0.5], [38, 0.25], [38, 0.25]
  ],
  "velocity": {
    "strong": 102,
    "intermediate": 96,
    "weak": 92
  }
}